Workbook

Sheet Daily_Headcount_Report
A1: Daily Headcount Report
A2: ="Generated: " & TEXT(TODAY(), "dd-mmm-yyyy") & " | Refreshes automatically when Raw_Departments updates" -> Generated: 29-Jul-2026 | Refreshes automatically when Raw_Departments updates
A4: Department | B4: Target Headcount 2026 | C4: Current Headcount | D4: Gap to Target | E4: % to Target | F4: Attrition % (All-Time) | G4: Status
A5: =Raw_Departments!B5 -> Engineering | B5: =Raw_Departments!C5 -> 820 | C5: =Raw_Departments!D5 -> 744 | D5: =B5-C5 -> 76 | E5: =C5/B5 -> 0.90731707 | F5: =Raw_Departments!F5/Raw_Departments!E5 -> 0.092682927 | G5: =IF(D5>50,"Hiring Gap - High Priority",IF(D5>0,"On Track","At/Above Target")) -> Hiring Gap - High Priority
A6: =Raw_Departments!B6 -> Sales | B6: =Raw_Departments!C6 -> 400 | C6: =Raw_Departments!D6 -> 329 | D6: =B6-C6 -> 71 | E6: =C6/B6 -> 0.8225 | F6: =Raw_Departments!F6/Raw_Departments!E6 -> 0.096153846 | G6: =IF(D6>50,"Hiring Gap - High Priority",IF(D6>0,"On Track","At/Above Target")) -> Hiring Gap - High Priority
A7: =Raw_Departments!B7 -> Human Capital | B7: =Raw_Departments!C7 -> 115 | C7: =Raw_Departments!D7 -> 108 | D7: =B7-C7 -> 7 | E7: =C7/B7 -> 0.93913043 | F7: =Raw_Departments!F7/Raw_Departments!E7 -> 0.136 | G7: =IF(D7>50,"Hiring Gap - High Priority",IF(D7>0,"On Track","At/Above Target")) -> On Track
A8: =Raw_Departments!B8 -> Finance | B8: =Raw_Departments!C8 -> 220 | C8: =Raw_Departments!D8 -> 206 | D8: =B8-C8 -> 14 | E8: =C8/B8 -> 0.93636364 | F8: =Raw_Departments!F8/Raw_Departments!E8 -> 0.092511013 | G8: =IF(D8>50,"Hiring Gap - High Priority",IF(D8>0,"On Track","At/Above Target")) -> On Track
A9: =Raw_Departments!B9 -> Operations | B9: =Raw_Departments!C9 -> 400 | C9: =Raw_Departments!D9 -> 342 | D9: =B9-C9 -> 58 | E9: =C9/B9 -> 0.855 | F9: =Raw_Departments!F9/Raw_Departments!E9 -> 0.1023622 | G9: =IF(D9>50,"Hiring Gap - High Priority",IF(D9>0,"On Track","At/Above Target")) -> Hiring Gap - High Priority
A10: =Raw_Departments!B10 -> Marketing | B10: =Raw_Departments!C10 -> 195 | C10: =Raw_Departments!D10 -> 186 | D10: =B10-C10 -> 9 | E10: =C10/B10 -> 0.95384615 | F10: =Raw_Departments!F10/Raw_Departments!E10 -> 0.088235294 | G10: =IF(D10>50,"Hiring Gap - High Priority",IF(D10>0,"On Track","At/Above Target")) -> On Track
A11: =Raw_Departments!B11 -> Data & Analytics | B11: =Raw_Departments!C11 -> 300 | C11: =Raw_Departments!D11 -> 260 | D11: =B11-C11 -> 40 | E11: =C11/B11 -> 0.86666667 | F11: =Raw_Departments!F11/Raw_Departments!E11 -> 0.068100358 | G11: =IF(D11>50,"Hiring Gap - High Priority",IF(D11>0,"On Track","At/Above Target")) -> On Track
A12: TOTAL | B12: =SUM(B5:B11) -> 2450 | C12: =SUM(C5:C11) -> 2175 | D12: =SUM(D5:D11) -> 275 | E12: =C12/B12 -> 0.8877551 | F12: =AVERAGE(F5:F11) -> 0.096577949

Sheet Raw_Departments
A1: RAW DATA — Department Headcount Extract (source: HRIS export, as of 2026-07-01)
A2: This tab simulates a raw system export. Reporting tabs reference these cells via formulas.
A4: Dept Id | B4: Dept Name | C4: Target Headcount 2026 | D4: Current Headcount | E4: Total Ever Hired | F4: Exits | G4: Avg Engagement | H4: Avg Salary
A5: 1 | B5: Engineering | C5: 820 | D5: 744 | E5: 820 | F5: 76 | G5: 3.6 | H5: 1695782
A6: 2 | B6: Sales | C6: 400 | D6: 329 | E6: 364 | F6: 35 | G6: 3.57 | H6: 1734788
A7: 3 | B7: Human Capital | C7: 115 | D7: 108 | E7: 125 | F7: 17 | G7: 3.71 | H7: 1638992
A8: 4 | B8: Finance | C8: 220 | D8: 206 | E8: 227 | F8: 21 | G8: 3.5 | H8: 1652604
A9: 5 | B9: Operations | C9: 400 | D9: 342 | E9: 381 | F9: 39 | G9: 3.53 | H9: 1612835
A10: 6 | B10: Marketing | C10: 195 | D10: 186 | E10: 204 | F10: 18 | G10: 3.64 | H10: 1656373
A11: 7 | B11: Data & Analytics | C11: 300 | D11: 260 | E11: 279 | F11: 19 | G11: 3.53 | H11: 1574728

Sheet Raw_Recruitment
A1: RAW DATA — Recruitment Funnel Extract (source: ATS export, by quarter & department)
A3: Quarter | B3: Dept Id | C3: Dept Name | D3: Applied | E3: Screened | F3: Interviewed | G3: Offered | H3: Hired
A4: 2025-Q1 | B4: 1 | C4: Engineering | D4: 351 | E4: 175 | F4: 87 | G4: 37 | H4: 25
A5: 2025-Q1 | B5: 2 | C5: Sales | D5: 212 | E5: 84 | F5: 34 | G5: 14 | H5: 11
A6: 2025-Q1 | B6: 3 | C6: Human Capital | D6: 219 | E6: 97 | F6: 47 | G6: 18 | H6: 13
A7: 2025-Q1 | B7: 4 | C7: Finance | D7: 458 | E7: 237 | F7: 113 | G7: 45 | H7: 29
A8: 2025-Q1 | B8: 5 | C8: Operations | D8: 134 | E8: 70 | F8: 31 | G8: 13 | H8: 8
A9: 2025-Q1 | B9: 6 | C9: Marketing | D9: 343 | E9: 140 | F9: 62 | G9: 26 | H9: 17
A10: 2025-Q1 | B10: 7 | C10: Data & Analytics | D10: 157 | E10: 83 | F10: 47 | G10: 22 | H10: 14
A11: 2025-Q2 | B11: 1 | C11: Engineering | D11: 308 | E11: 141 | F11: 70 | G11: 25 | H11: 20
A12: 2025-Q2 | B12: 2 | C12: Sales | D12: 267 | E12: 146 | F12: 79 | G12: 34 | H12: 27
A13: 2025-Q2 | B13: 3 | C13: Human Capital | D13: 154 | E13: 78 | F13: 32 | G13: 12 | H13: 9
A14: 2025-Q2 | B14: 4 | C14: Finance | D14: 388 | E14: 194 | F14: 109 | G14: 44 | H14: 38
A15: 2025-Q2 | B15: 5 | C15: Operations | D15: 102 | E15: 55 | F15: 32 | G15: 13 | H15: 10
... A45: 2026-Q2 | B45: 7 | C45: Data & Analytics | D45: 331 | E45: 148 | F45: 68 | G45: 26 | H45: 22

Sheet Recruitment_Funnel_Report
A1: Recruitment Funnel Report — Latest Quarter
A2: 2026-Q2
A3: Quarter filter cell above (A2) — change it to any quarter in Raw_Recruitment to refresh this report.
A4: Department | B4: Applied | C4: Screened | D4: Interviewed | E4: Offered | F4: Hired | G4: Applied to Screen % | H4: Screen to Interview % | I4: Interview to Offer % | J4: Offer to Hire % | K4: Overall Conversion %
A5: Engineering | B5: =SUMIFS(Raw_Recruitment!D:D,Raw_Recruitment!C:C,A5,Raw_Recruitment!A:A,$A$2) -> 202 | C5: =SUMIFS(Raw_Recruitment!E:E,Raw_Recruitment!C:C,A5,Raw_Recruitment!A:A,$A$2) -> 106 | D5: =SUMIFS(Raw_Recruitment!F:F,Raw_Recruitment!C:C,A5,Raw_Recruitment!A:A,$A$2) -> 62 | E5: =SUMIFS(Raw_Recruitment!G:G,Raw_Recruitment!C:C,A5,Raw_Recruitment!A:A,$A$2) -> 25 | F5: =SUMIFS(Raw_Recruitment!H:H,Raw_Recruitment!C:C,A5,Raw_Recruitment!A:A,$A$2) -> 20 | G5: =IFERROR(C5/B5,0) -> 0.52475248 | H5: =IFERROR(D5/C5,0) -> 0.58490566 | I5: =IFERROR(E5/D5,0) -> 0.40322581 | J5: =IFERROR(F5/E5,0) -> 0.8 | K5: =IFERROR(F5/B5,0) -> 0.099009901
A6: Sales | B6: =SUMIFS(Raw_Recruitment!D:D,Raw_Recruitment!C:C,A6,Raw_Recruitment!A:A,$A$2) -> 426 | C6: =SUMIFS(Raw_Recruitment!E:E,Raw_Recruitment!C:C,A6,Raw_Recruitment!A:A,$A$2) -> 186 | D6: =SUMIFS(Raw_Recruitment!F:F,Raw_Recruitment!C:C,A6,Raw_Recruitment!A:A,$A$2) -> 103 | E6: =SUMIFS(Raw_Recruitment!G:G,Raw_Recruitment!C:C,A6,Raw_Recruitment!A:A,$A$2) -> 41 | F6: =SUMIFS(Raw_Recruitment!H:H,Raw_Recruitment!C:C,A6,Raw_Recruitment!A:A,$A$2) -> 31 | G6: =IFERROR(C6/B6,0) -> 0.43661972 | H6: =IFERROR(D6/C6,0) -> 0.55376344 | I6: =IFERROR(E6/D6,0) -> 0.39805825 | J6: =IFERROR(F6/E6,0) -> 0.75609756 | K6: =IFERROR(F6/B6,0) -> 0.072769953
A7: Human Capital | B7: =SUMIFS(Raw_Recruitment!D:D,Raw_Recruitment!C:C,A7,Raw_Recruitment!A:A,$A$2) -> 325 | C7: =SUMIFS(Raw_Recruitment!E:E,Raw_Recruitment!C:C,A7,Raw_Recruitment!A:A,$A$2) -> 156 | D7: =SUMIFS(Raw_Recruitment!F:F,Raw_Recruitment!C:C,A7,Raw_Recruitment!A:A,$A$2) -> 89 | E7: =SUMIFS(Raw_Recruitment!G:G,Raw_Recruitment!C:C,A7,Raw_Recruitment!A:A,$A$2) -> 39 | F7: =SUMIFS(Raw_Recruitment!H:H,Raw_Recruitment!C:C,A7,Raw_Recruitment!A:A,$A$2) -> 27 | G7: =IFERROR(C7/B7,0) -> 0.48 | H7: =IFERROR(D7/C7,0) -> 0.57051282 | I7: =IFERROR(E7/D7,0) -> 0.43820225 | J7: =IFERROR(F7/E7,0) -> 0.69230769 | K7: =IFERROR(F7/B7,0) -> 0.083076923
A8: Finance | B8: =SUMIFS(Raw_Recruitment!D:D,Raw_Recruitment!C:C,A8,Raw_Recruitment!A:A,$A$2) -> 451 | C8: =SUMIFS(Raw_Recruitment!E:E,Raw_Recruitment!C:C,A8,Raw_Recruitment!A:A,$A$2) -> 203 | D8: =SUMIFS(Raw_Recruitment!F:F,Raw_Recruitment!C:C,A8,Raw_Recruitment!A:A,$A$2) -> 116 | E8: =SUMIFS(Raw_Recruitment!G:G,Raw_Recruitment!C:C,A8,Raw_Recruitment!A:A,$A$2) -> 35 | F8: =SUMIFS(Raw_Recruitment!H:H,Raw_Recruitment!C:C,A8,Raw_Recruitment!A:A,$A$2) -> 28 | G8: =IFERROR(C8/B8,0) -> 0.45011086 | H8: =IFERROR(D8/C8,0) -> 0.57142857 | I8: =IFERROR(E8/D8,0) -> 0.30172414 | J8: =IFERROR(F8/E8,0) -> 0.8 | K8: =IFERROR(F8/B8,0) -> 0.062084257
A9: Operations | B9: =SUMIFS(Raw_Recruitment!D:D,Raw_Recruitment!C:C,A9,Raw_Recruitment!A:A,$A$2) -> 425 | C9: =SUMIFS(Raw_Recruitment!E:E,Raw_Recruitment!C:C,A9,Raw_Recruitment!A:A,$A$2) -> 205 | D9: =SUMIFS(Raw_Recruitment!F:F,Raw_Recruitment!C:C,A9,Raw_Recruitment!A:A,$A$2) -> 96 | E9: =SUMIFS(Raw_Recruitment!G:G,Raw_Recruitment!C:C,A9,Raw_Recruitment!A:A,$A$2) -> 34 | F9: =SUMIFS(Raw_Recruitment!H:H,Raw_Recruitment!C:C,A9,Raw_Recruitment!A:A,$A$2) -> 27 | G9: =IFERROR(C9/B9,0) -> 0.48235294 | H9: =IFERROR(D9/C9,0) -> 0.46829268 | I9: =IFERROR(E9/D9,0) -> 0.35416667 | J9: =IFERROR(F9/E9,0) -> 0.79411765 | K9: =IFERROR(F9/B9,0) -> 0.063529412
A10: Marketing | B10: =SUMIFS(Raw_Recruitment!D:D,Raw_Recruitment!C:C,A10,Raw_Recruitment!A:A,$A$2) -> 405 | C10: =SUMIFS(Raw_Recruitment!E:E,Raw_Recruitment!C:C,A10,Raw_Recruitment!A:A,$A$2) -> 220 | D10: =SUMIFS(Raw_Recruitment!F:F,Raw_Recruitment!C:C,A10,Raw_Recruitment!A:A,$A$2) -> 109 | E10: =SUMIFS(Raw_Recruitment!G:G,Raw_Recruitment!C:C,A10,Raw_Recruitment!A:A,$A$2) -> 50 | F10: =SUMIFS(Raw_Recruitment!H:H,Raw_Recruitment!C:C,A10,Raw_Recruitment!A:A,$A$2) -> 42 | G10: =IFERROR(C10/B10,0) -> 0.54320988 | H10: =IFERROR(D10/C10,0) -> 0.49545455 | I10: =IFERROR(E10/D10,0) -> 0.4587156 | J10: =IFERROR(F10/E10,0) -> 0.84 | K10: =IFERROR(F10/B10,0) -> 0.1037037
A11: Data & Analytics | B11: =SUMIFS(Raw_Recruitment!D:D,Raw_Recruitment!C:C,A11,Raw_Recruitment!A:A,$A$2) -> 331 | C11: =SUMIFS(Raw_Recruitment!E:E,Raw_Recruitment!C:C,A11,Raw_Recruitment!A:A,$A$2) -> 148 | D11: =SUMIFS(Raw_Recruitment!F:F,Raw_Recruitment!C:C,A11,Raw_Recruitment!A:A,$A$2) -> 68 | E11: =SUMIFS(Raw_Recruitment!G:G,Raw_Recruitment!C:C,A11,Raw_Recruitment!A:A,$A$2) -> 26 | F11: =SUMIFS(Raw_Recruitment!H:H,Raw_Recruitment!C:C,A11,Raw_Recruitment!A:A,$A$2) -> 22 | G11: =IFERROR(C11/B11,0) -> 0.44712991 | H11: =IFERROR(D11/C11,0) -> 0.45945946 | I11: =IFERROR(E11/D11,0) -> 0.38235294 | J11: =IFERROR(F11/E11,0) -> 0.84615385 | K11: =IFERROR(F11/B11,0) -> 0.066465257

Sheet Headcount_Forecast
A1: Headcount Forecast — What-If Model
A2: Yellow cells are adjustable assumptions. All results recalculate automatically.
A4: Assumptions
A5: Planning horizon (months) | B5: 6
A6: Expected monthly attrition rate (company-wide) | B6: 0.012
A7: Average hire-to-offer lead time (weeks) | B7: 8
A8: Average offer-to-hire conversion rate | B8: =AVERAGE(Recruitment_Funnel_Report!K5:K11) -> 0.078662772
A10: Department Forecast
A11: Department | B11: Current Headcount | C11: Target Headcount | D11: Net New Hires Needed | E11: Expected Attrition (Horizon) | F11: Total Hires Required | G11: Applications Needed (at current conversion %)
A12: =Daily_Headcount_Report!A5 -> Engineering | B12: =Daily_Headcount_Report!C5 -> 744 | C12: =Daily_Headcount_Report!B5 -> 820 | D12: =MAX(C12-B12,0) -> 76 | E12: =ROUND(B12*$B$6*$B$5,0) -> 54 | F12: =D12+E12 -> 130 | G12: =IFERROR(F12/Recruitment_Funnel_Report!K5,F12/0.08) -> 1313
A13: =Daily_Headcount_Report!A6 -> Sales | B13: =Daily_Headcount_Report!C6 -> 329 | C13: =Daily_Headcount_Report!B6 -> 400 | D13: =MAX(C13-B13,0) -> 71 | E13: =ROUND(B13*$B$6*$B$5,0) -> 24 | F13: =D13+E13 -> 95 | G13: =IFERROR(F13/Recruitment_Funnel_Report!K6,F13/0.08) -> 1305.4839
A14: =Daily_Headcount_Report!A7 -> Human Capital | B14: =Daily_Headcount_Report!C7 -> 108 | C14: =Daily_Headcount_Report!B7 -> 115 | D14: =MAX(C14-B14,0) -> 7 | E14: =ROUND(B14*$B$6*$B$5,0) -> 8 | F14: =D14+E14 -> 15 | G14: =IFERROR(F14/Recruitment_Funnel_Report!K7,F14/0.08) -> 180.55556
A15: =Daily_Headcount_Report!A8 -> Finance | B15: =Daily_Headcount_Report!C8 -> 206 | C15: =Daily_Headcount_Report!B8 -> 220 | D15: =MAX(C15-B15,0) -> 14 | E15: =ROUND(B15*$B$6*$B$5,0) -> 15 | F15: =D15+E15 -> 29 | G15: =IFERROR(F15/Recruitment_Funnel_Report!K8,F15/0.08) -> 467.10714
A16: =Daily_Headcount_Report!A9 -> Operations | B16: =Daily_Headcount_Report!C9 -> 342 | C16: =Daily_Headcount_Report!B9 -> 400 | D16: =MAX(C16-B16,0) -> 58 | E16: =ROUND(B16*$B$6*$B$5,0) -> 25 | F16: =D16+E16 -> 83 | G16: =IFERROR(F16/Recruitment_Funnel_Report!K9,F16/0.08) -> 1306.4815
A17: =Daily_Headcount_Report!A10 -> Marketing | B17: =Daily_Headcount_Report!C10 -> 186 | C17: =Daily_Headcount_Report!B10 -> 195 | D17: =MAX(C17-B17,0) -> 9 | E17: =ROUND(B17*$B$6*$B$5,0) -> 13 | F17: =D17+E17 -> 22 | G17: =IFERROR(F17/Recruitment_Funnel_Report!K10,F17/0.08) -> 212.14286
A18: =Daily_Headcount_Report!A11 -> Data & Analytics | B18: =Daily_Headcount_Report!C11 -> 260 | C18: =Daily_Headcount_Report!B11 -> 300 | D18: =MAX(C18-B18,0) -> 40 | E18: =ROUND(B18*$B$6*$B$5,0) -> 19 | F18: =D18+E18 -> 59 | G18: =IFERROR(F18/Recruitment_Funnel_Report!K11,F18/0.08) -> 887.68182
A19: TOTAL | B19: =SUM(B12:B18) -> 2175 | C19: =SUM(C12:C18) -> 2450 | D19: =SUM(D12:D18) -> 275 | E19: =SUM(E12:E18) -> 158 | F19: =SUM(F12:F18) -> 433 | G19: =SUM(G12:G18) -> 5672.4527
